ladybug_grasshopper_dotnet/Ladybug.Executor.exe
ladybug_grasshopper_dotnet/Ladybug.Grasshopper.gha
ladybug_grasshopper_dotnet/__init__.py
ladybug_grasshopper_dotnet-1.3.4.dist-info/LICENSE
ladybug_grasshopper_dotnet-1.3.4.dist-info/METADATA
ladybug_grasshopper_dotnet-1.3.4.dist-info/WHEEL
ladybug_grasshopper_dotnet-1.3.4.dist-info/top_level.txt
ladybug_grasshopper_dotnet-1.3.4.dist-info/RECORD
