Metadata-Version: 2.1
Name: ladybug-grasshopper-dotnet
Version: 1.3.4
Summary: Contains the .gha files for the Ladybug Grasshopper Plugin.
Home-page: https://github.com/ladybug-tools/ladybug-grasshopper-dotnet
Author: Ladybug Tools
Author-email: info@ladybug.tools
License: AGPL-3.0
Classifier: License :: OSI Approved :: GNU Affero General Public License v3
Classifier: Operating System :: OS Independent
License-File: LICENSE
